envrun/__init__.py
envrun/__main__.py
envrun/env.py
envrun/runner.py
envrun/dotenv/__init__.py
envrun/dotenv/compat.py
envrun/dotenv/parser.py
envrun_python-0.0.3.dist-info/LICENSE
envrun_python-0.0.3.dist-info/METADATA
envrun_python-0.0.3.dist-info/WHEEL
envrun_python-0.0.3.dist-info/entry_points.txt
envrun_python-0.0.3.dist-info/top_level.txt
envrun_python-0.0.3.dist-info/RECORD
