Metadata-Version: 2.1
Name: envrun-python
Version: 0.0.3
Summary: Run command with specified environment-variable file
Home-page: https://github.com/ericgj/envrun-python
Author: Eric Gjertsen
Author-email: ericgj72@gmail.com
License: MIT
Platform: UNKNOWN
Classifier: Development Status :: 2 - Pre-Alpha
Classifier: License :: OSI Approved :: MIT License
Classifier: Programming Language :: Python
Classifier: Programming Language :: Python :: 2
Classifier: Programming Language :: Python :: 2.7
Classifier: Programming Language :: Python :: 3
Classifier: Programming Language :: Python :: 3.6
Classifier: Programming Language :: Python :: 3.7
Requires-Dist: ruamel.yaml
